topologicalMachinelearningTobiasMadsen.py
topologicalMachinelearningTobiasMadsen-0.0.1.dist-info/LICENSE.txt
topologicalMachinelearningTobiasMadsen-0.0.1.dist-info/METADATA
topologicalMachinelearningTobiasMadsen-0.0.1.dist-info/WHEEL
topologicalMachinelearningTobiasMadsen-0.0.1.dist-info/top_level.txt
topologicalMachinelearningTobiasMadsen-0.0.1.dist-info/RECORD
